{
  "character_id": "52f0fcd1-8578-45cd-8e60-68e5038bc45a",
  "title": "wj元旦彩蛋 ｜2020谈莎士比亚：不朽的喜剧角色福斯塔夫 (2).md",
  "raw_content": "岂乔二人的镍国羽， 人钟征多上目百上肛晶J，\n\n另一种是吹着口哨的。他们的差别不在于\n口袋里钱的多少，而在于天性是否快乐。\n新年到了 ，大家不妨打起响指 ，吹起口\n哨，过好当下的生活。\n\n欢迎你在留言区，写下自己的新年愿望，\n\n再次祝大家新年快乐。\n\n吴军.数学通识50讲\n\n用户留言  7 我要久计\nAa  四  天  是\n\n字号  写留言  70  请朋友读",
  "source_type": "fragment_expression",
  "confidence": "B",
  "tags": [
    "file_upload"
  ],
  "created_at": "2026-06-14T00:03:42.834501",
  "cleaned_content": "",
  "url": null,
  "word_count": 181,
  "extracted_triples": [],
  "id": "11f64ec8-ab61-4f80-b7a8-3a1e7680d762"
}