{
  "character_id": "52f0fcd1-8578-45cd-8e60-68e5038bc45a",
  "title": "wj32｜积分：如何从微观趋势了解宏观变化 (2).md",
  "raw_content": "二让加加的积分，是一个加要职才\n人看到的量，因此内有送后效应。下面我\n们不铬用积分的原理，量化分析一下飞办\n加于为什么和和但。\n\n我们候设飞的质量等100二克，从这\n到锰心之间，质量的中心大的在志轴必\n0.32米,转动的手全也安在个位置，这\n村一四当于是2炒。，\n\n我们用200牛全的力办这个飞轮，这征一\n个不算太小的力，根据牛信第二定律，复\n下来飞轮有一个恒定的给加速度，即2米/\n动*2，如果我们转化成角加速度，就是1\n岗/防^2，台者洪，一入名我们可以飞欠\n\n秒，达下本加。\n\n所下来们来分析一下加速度、思诺和转\n动虹高 国雪的关系。 只要开络用力,，\n间训得了加速度，是1米/副的平方。\n控下来，经这1种名的加速，它的转速到\n生各一转，但这时已经过去了1各种，这卫\n是积分的二应。\n\n这时再看它直过的上元，是0.5图这也中\n请后效应引起的。事实上，它完且一轿的\n时间大的是1.4秒。 也评讽，加度比加到\n二有涝后，王训比过度有清后。挫下来\n在第二秒，它达到每两图的带度，这时\n飞地从好转丙加，此后飞四轩直亿，\n果机转过的国人以快速提升。\n\n公式和数扫由列了出来  SR\n\n2 ep\nee np\n\nar1m，4\n\n00.32尖，玫林符-国2m\n\n面E0.5、2\n\n男中的因经加速度，它溉有下时，红具\n是过度，它有漠后效应，伺呈不大。 基线\n是下高，是加如两次积分的结果，尝后\n分应很大。但是一下飞办飞人地转动，如\n困有一个人起往相反方向再力，让它沽如\n并且拓转，也是非常国难的，罗要-一段时\n间，才能各认为要然后再经过一和\n时间才能他转，并抵滑拓一开抬转过的国\n\n才在《和可方法论) 的206盾们谈过“J脂\n钱和涝后效应”，其更本贰的原理就在于\n\n怎么用?\n\n其实在生应和工作中，我的努力，训如\n同风力，你今天隐上熏力了，你是知才\n的，介是得一和时间，才会并你的\n他力;你的有力和一时间。\n你的成续和业继而 0\n不会马上得  Ce\n\n和  二 认可， 才\n\n汪- wmas umn\n\n人再一个很大的昌上就在于，人在开让\n力划一加同，训振明力马上提升，钛后\n疝加的人马上肖定自己，忘记了积累效\n坦。 如果到人不定居，愧就贫和世界对\n全不公平。而当人开始放松，一开始并没\n有出问题,但是会带新出问题， 这时大各\n分人只会自己这人事情没有做好，而不\n\n子。\n\n我们讲丙分，不是学一个知识点，而\n是通过积分交应，提逢我们的认识水平\n\n的现旬。\n\n罗考题:在\n\n的认呈多少?\n\n下一讲，我们经统讨论如何换一可动态的\n光去扫问是的最优解。 我们下一齐再\n由。",
  "source_type": "fragment_expression",
  "confidence": "B",
  "tags": [
    "file_upload"
  ],
  "created_at": "2026-06-14T00:03:12.778435",
  "cleaned_content": "",
  "url": null,
  "word_count": 1076,
  "extracted_triples": [],
  "id": "30c306a7-5ad2-4e4d-8bdf-bf2b77556617"
}