{
  "character_id": "7720505d-c6cd-4a7e-abf9-fca2c8c59b52",
  "title": "lr10｜还原大前提：过去有效，现在失效，怎么办？2.md",
  "raw_content": "押”这个模式，就不再是必须了。\n\n— BARA —\n\n任何商业模式，或者说系统能够成立，都\n有“隐藏的大前提” 。大前提消失，看不\n见的东西不见了，因果链就会断裂，系统\n就会失效。\n\n所以，过去有效，现在失效，这时你要条\n件反射地想到，一定是它所依赖的某企隐\nHAA BEAT > 那怎么办(还原大前\n提。\n\n怎么还原大前提? 从三个地方，找到大前\n提可能的藏身之处，它们是: 时间前提、\n空间前提，和技术前提。\n\n我们无法在画因果链的最开始，就把所有\n大前提都列在纸上，这样可能100张纸都\n不够。但是我们要知道，一定有些我们看\n\n不见的东西是被默认存在的。一旦遇\n到“过去有效、现在失效”的问题，就要\n开始寻找“隐藏的大前提” 。\n\n好的，这一讲就讲到这里 。下一讲，我们\n进行用模型解决难题的第二项训练: SE\n边界墙 。\n\n今天我留给你一个思考题。你的公局\n赚钱吗? 你能还原三个，你公司能赚\n钱的“隐藏的大前提”吗? 欢迎你在\n留言区和我互动。\n\n不抽象，就无法深入思考; 不还原\n就看不到本来面目。这里是《刘润 -\n商业洞察力30讲》。我们下一讲，再\n见。\n\n《刘润 商业洞察力30讲》 BE\n看透复杂世界，破解决策难题\n\n刘浊:商业润宗力30讲\n\n版权归但到App所有，未经许可不得转载\n\nAa  Y  i  zi",
  "source_type": "fragment_expression",
  "confidence": "A",
  "tags": [
    "file_upload"
  ],
  "created_at": "2026-06-14T09:33:40.142249",
  "cleaned_content": "",
  "url": null,
  "word_count": 564,
  "extracted_triples": [],
  "id": "37942040-b11c-48c6-9381-2e6a096671e3"
}