{
  "character_id": "52f0fcd1-8578-45cd-8e60-68e5038bc45a",
  "title": "wj02｜解开世界之谜的三篇诺贝尔奖论文.md",
  "raw_content": "02 | 解开世界之这的三\n\n@ RE - 信息论40讲\n5)\nr >) 02 | 解开世界之谜的三篇.， 山\n\n你好，欢迎来到我的《信息论40讲》。\n\n上一讲，我为你介绍了改变世界的3比特信\n息，希望你能体会到信息的重要，也认识\n到它其实比我们了解的，要复杂得多 。但\n是信息论真的是一门复杂深奥的学科吗?\n\n的论文, 你会感受到信息的简洁之美, 以\n及传递效率的重要性。\n\n关。我常说，我们这一代人非常幸运，因\n为在我们这一代生活的世界 ，人类搞清楚\n了三个非常本源的问题, 也就是宇宙是如\n何产生的, 地球生命的共性和起点, 以及\n人类文明的起点。\n\n那么，宇宙到底是如何诞生的呢? 我们现\n在知道，宇宙是从一个体积无限小，温度\n近乎无限高的质点爆炸产生的，这就是今\n天大家认可的宇宙大爆炸理论 。\n\n根据这个理论，在大约138亿年前，那个\n质点发生了大爆炸 。在随后大约一个普\n\n克的时间里 ( 普朗克时间是能够度量的最\n小时间单位，大约是10的负44次方秒) ，\n重力场开始形成。\n\n到了大爆炸后的0.02秒，宇宙中出现了第\n\n丝光 。接着，宇宙中的一部分能量就变\n成了物质。几乎同时间 ，大量的能量转化\n为质子和中子，在这个过程中，宇宙中能\n量减少，物质增加。\n\n然后，随着宇宙的膨胀 、冷却，原子核、\n原子相继出现 。引力又让这些原子形成星\n云和天体 。再往后进化出生命，背后也有\n套规律在起作用 。\n\n也就是说宇宙在诞生的同时，就有了各种\n物理的法则 (Law) 在起作用，后来又有\n了化学和生物学的法则 ，它们都是宇宙固\n有的信息。\n\n《科技史纲60讲》中有读者问我:\n\n“和能量是烙界辕育的，是它诞生之初就存\nEN, BARERMBER? ”\n\n信息和能量一样 ，都是宇宙本身固有的特\n性。\n\n你可能要问，上述这些描述没有人看见，\n我们是怎么知道的呢? 物理学家们主要是\n通过两种方法推断出当时的场景的。\n\n当然，有些推断可信度高一些，有些低一\n些，世界上没有绝对的可靠，只有可靠性\n的高和低，信号和噪音比率的高和低 。从\n信息论上说，信息的可靠性就叫做置信\n度，我会在后面为你详细讲解。\n\n大爆炸存留至今的信息，其中最著名的发\n现是3K背景辐射，这是一种温度约为3K，\n也就是-270摄氏度，而且充满整个宇宙的\n电磁辐射 。\n\n在大爆炸大约1秒的时候，宇宙中最初形成\n的中子因为不带电，率先冲出宇宙这个大\n火球，弥散到宇宙的四周，它们所携带的\n能量形成了今天宇宙的背景辐射 。当然随\n着时间越来越长，宇宙越来越冷，背景辐\n射的温度会越来越低 。\n\n如果宇宙大爆炸理论是正确的，那么应该\n\n的这些背景辐射，而且今天它们的温度不\n应该太高。\n\n964年，贝尔实验室的工程师阿诺' 彭齐\n亚斯和罗伯特' 威尔逊在无意中发现了这\n种宇宙背景辐射 。他们架设了一个天线，\n本来是要接收卫星发回的信号的 。为了检\n测这个天线的性能，他们将天线对准天空\n中没有卫星的方向进行测量，结果发现有\n\ntS eee ee ee oe ee Ae ee\n\n关。\n\n系统有问题。1965年初，他们对天线进行\n了彻底检查，甚至把天线上的鸽子富和鸟\n凌都清除了一遍，然而这个噪声仍然存\n在。于是他们发表论文，正式宣布了这个\n发现，整篇论文只有两页纸。人类后来又\n民据背景辐射的温度，以及扩张的速度等\n信息，倒推出宇宙有138亿年的历史。\n\n978 年，彭齐亚斯和威尔逊因为那个偶\n然的发现和那篇两页纸的论文，“幸运\n也”获得了诺贝尔物理学奖。\n\n写很长，它们里面的信和\n我们上一讲讲到的，对于一件过去大家不\n知道的事情，现在知道了，信息量就大，\n对于一件大家基本上了解的  ，即使你\n的文章写得再长，信息量都有限。\n\n我过去多次讲，提出问题比解决问题更习\n，因为提出问题的人，开创了一个重\n的却是完全未知的领域，回答问题并且给\n出最初解答的人，  通常只是在某种认\n\n息，因此贡献有限，被认可的程度不高 。\n\n法, 就是用空间换时间。\n\n我们知道宇密有138亿年的历史，在离我\n们非常遥远的宇宙空间，光传递到我们这\n里需要很多很多年，因此这其实记录的就\n\n看到的很多星辰，它们可能已经不存在\n也;我们只不过看到的是它们的快照和化\n石。\n\n所以，只要观测到138亿年前的星系，就\n能知道宇宙早期的情况，事实上人们也做\n到了。这就是用空间换时间，在信息论\n上，这实际是信息等价性的体现，关于信\n息的等价性我们后面会讲到 。\n\n好，刚才为你介绍了两种推断宇宙诞生的\n方法，一是寻找3K背景辐射, 二是以空间\n换时间。 其中提到了两个要点; 第一, 信息\n是宇宙本身固有的属性; 第二, 在一个领\n域的贡献大小, 不在于你提供了多少材\n料, 而在于提供了多少信息量。\n\n但事实上，今天对于最早期宇宙状态的描\n使用各种理论模型推导出来的，要证\n\n们还需要后人的努力。\n\n‘tt\n\nQt A\n\n人类一方面对外部世界很好奇，比如设法\n\n了解宇宙起源和演变的信息，另一方面\n对自身也很好奇，试图去了解生命起源和\n传承的信息 ，这些信息本身，也是世界所\n固有的。\n\n关于这一点我在《科技史纲60讲》里介绍\n遗传和DNA时已经介绍了 。接下来，我想\n从信息论的角度出发，为你介绍这篇诺奖\n论文。\n\n首先，沃森和克里克获得诺贝尔奖的论文\n也只有一页半纸，我把它附在了课程的后\n面，有兴趣阅读英文原文的朋友可以读一\n\n读。\n\n当然有人可能会问，这么高深的论文我能\nZEB? 你只要有比较好的大学教育基\n础，就能读懂。这也就是说，一篇好的论\n文，一方面需要信息量高，另一方面需要\n在信息传播上效率高 。大家都读不懂的论\n文，信息传递的效率就低 。\n\n怎样利用信息论原理，做到信息传播的\n效率，是我们这门课要讲的重要内容 。\n\n讲演前的指导，我给大家最多的建议就\nz=, FRGSERMEURENA, Be\n简，要保证对方听懂自己最核心的想法，\n这就够了 。我阅读过几十篇的诺贝尔奖的\n论文，很少有超过10页纸的。\n\n其次，沃森和克里克这篇论文的逻辑很清\n晰，他们首先否定了鲍林之前的三螺旋结\n构，因为和一些已知的信息不相符。\n\n然后，他们提出了自己的双螺旋模型，那\n一段关键描述只有105个单词 (包括the，\na ，so这些虚词) 。最后，他们说明了自\n姜的模型同感尔全本 宣兰古林观帘到|的\n\n沃森和克里克等人提供了一个“利\n\n看到的信息 ，解释看不到的信息”\n案例 。他们的论文和理论也验证了\n中一条被称为“奥卡姆剃刀”的原则\n\n这条原则用牛顿的话讲，就是“我们需要\n承认，自然事物各种现象的真实而有效的\n原因，除了它自身以外再无须其他”。我\n想这是我们在认识世界时应该有的态度 。\n关于奥卡姆剃刀原则 ，我们后面会专门\n\n讲。\n\n在了解了和DNA相关的信息之后，\n\n需的信息 ，RNA会在指导合成蛋\n继续将这些信息传递下去 。\n\n=~\n\n质时，\n\n的。\n\n命的活动，并且保护我们自身 。\n\n奖获得者科比尔卡的话讲，这涉及到G蛋\n\n之间的通信。\n\nAa  四  iv)\n\n是你可能还有一个疑问，就是有了蛋\n后，生命体是如何工作的? 比如\n\n胞是如何接受有益的物质，拒绝有害的\n物质，保护自身细胞 ，杀死有害的细胞\n\n细胞里显然没有大脑，不是通过思考作出\n理性判断 。但是蛋白质本身会对多\n激信号作出反应，这些反应维持着我们生",
  "source_type": "fragment_expression",
  "confidence": "B",
  "tags": [
    "file_upload"
  ],
  "created_at": "2026-06-14T00:01:39.882842",
  "cleaned_content": "",
  "url": null,
  "word_count": 3048,
  "extracted_triples": [],
  "id": "41b676bd-2240-4aa8-9c45-01d8861fc376"
}