{
  "character_id": "72bce317-1f93-4270-8a65-27b72cfb81f6",
  "title": "jy96 问答：怎么才能既自信又谦虚.md",
  "raw_content": "# 问答：怎么才能既自信又谦虚\n\n问答：怎么才能既自信又谦虚？\n\n来自日课：你躲不开政治和权力\n\n读者 戚志光：万 sir，权力是否与责任有对应的关系呢？我朴素的理解\n\n是，权力越大，责任就越大，一个人必须要承担起相应的责任，才配得\n\n上所拥有的权力。但是现实中也确实有人以权谋私，把责任甩得远远的，\n\n而且还能长时间地通过这种方式占据着权力。\n\n万维钢回复——\n\n你说的很对。「责任」有两种意思，一个是 responsibility，意思这个\n\n事儿是你管的，事情的结果是好是坏，都主要是你造成的，事情办砸了\n\n你应该感到愧疚——这里说的是天然的责任。这里的确是权力越大责任\n\n越大。\n\f责任的另一层意思是「追责」，是 accountability，是出了事儿拿你是\n\n问，追究你的责任。这个，可就不一定是权力越大责任越大了。因为掌\n\n权者完全可以运用权力给自己推卸责任，让别人当替罪羊，有了功劳归\n\n自己，有了错误归下属，往往可以权力越大，责任越小。\n\n这就是为什么成熟的制度一定要有一个追责机制。这样的机制一定是外\n\n加的，是底层力量的体现，而不是权力内生的。\n\f可是哪有那么多成熟制度呢？所以权力规则的第七条，恰恰就是权力可\n\n以让你免责。咱们到时候再细说。\n\n读者 时间移民：万老师，权力是不是只能从人事斗争中获得？有没有\n\n其他途径？比如技术。\n\n万维钢回复——\n\n人事斗争往往涉及到直接的冲突，造成明确的敌对关系，的确是不太好\n\n的。我们后面会讲到，很多时候你得到权力并不需要直接跟人对抗。比\n\n如你处在一个关键岗位，你的工作业绩能被领导看到，你的竞争对手虽\n\n然能力很强，可是他的业绩是众人看不到的，那么你自然就胜出了。这\n\n里你没有给对手造成直接的痛感，你完全可以说：哎呀你说咋搞的，我\n\n也知道老兄你的能力比我强，可是上面非让我干，真是没办法！\n\n虽是如此，但是请注意：权力任何时候都是零和游戏，它总是一个跟人\n\n争、而不是跟机器、跟考试题争的项目。你上去，就意味着别人上不去，\n\n而别人很想上去。所以你总是需要主动争取。你的争取动作可以是向上\n\n做工作而不是打压对手……但是我们千万不要抱有幻想，认为永远都不\n\n需要直接的人事斗争。越到高层，就越得面对人事斗争，包括直接打压\n\n对手。那是很不好看的游戏，咱们后面再讲。\n\f来自日课：克服顺民心态\n\n读者 自牧：夫唯不争，故天下莫能与之争。老子的这句名言是自欺欺\n\n人吗？\n\n万维钢回复——\n\n这句话被很多人理解错了。老子说的不争，是「江海」不与小溪流争，\n\n「圣人」不与老百姓争——之所以不争，是因为不在一个层面。\n\n简单说，运行平台的人不应该跟参与平台的人争。马云会让自己老婆开\n\n个淘宝店，然后多给老婆的店首页推荐吗？不会。马云的游戏是淘宝这\n\n个平台，而不是在淘宝开店。唐太宗看到有那么多读书人来参加科举，\n\n开心地说「天下英雄尽入吾彀中矣！」那你说他会让自己的儿子们也参\n\n加考试，完了让主考官多照顾照顾，给儿子考个状元吗？当然不会。\n\n如果有人一边运营着平台一边下场跟平台中的玩家争，又当裁判员又当\n\n运动员，这个平台必定就是不公平的，别人自然就要挑战一下你的权威；\n\n如果你有边界感，知道自己什么不能争，平台玩家自然不会跟你争。\n\n可是如果一个读书人误读了老子这句话，说参加科举考试争夺做官名额\n\n吃相太难看了，我这么有学问的人不屑于跟普通人争，唐太宗看我这么\n\n谦虚自然就会请我出山……这不有病吗？\n\f读者 吴下阿蒙：谦虚一直被认为最可贵的品质之一，是否领导者和谦\n\n虚天然矛盾？还是强者只有在充分展示能力后才能既自信又谦虚？\n\n万维钢回复——\n\n我们大约可以把「谦虚」分为三种。\n\n第一种是对「他人」的谦虚。虽然我很厉害，但是我跟谁都客气，总是\n\n尊重对方，从来不飞扬跋扈。爱因斯坦就是这种谦虚，但牛顿没有，牛\n\n顿经常看不起别的科学家。\n\n第二种是对「未知」的谦虚。虽然我经历过很多事情也读过很多书，但\n\n是我承认我的认知是有限的，眼前这个新局面对我来说很陌生，我不能\n\n生搬硬套老经验，我要多学习。做大事的人都应该有这种谦虚。牛顿有\n\n这样的谦虚，但爱因斯坦没有，爱因斯坦一心想要统一物理学。\n\n这两种谦虚，任何时候都是对的，没问题。\n\n第三种，却是对「自己」的谦虚：我不行，我不会，我觉得我做必定失\n\n败……这是不自信，是想要争夺权力的人必须避免的。\n\n以前我们讲格兰特的《重新思考》的时候讲过 [1]，自信有两种：一种\n\n是对自己能力的自信，一种是对自己手里掌握的工具的自信。\n\f理想的谦虚，是对自己的能力很自信的同时，怀疑自己可能暂时并不掌\n\n握解决问题最合适的工具，并且愿意为此探索一番。\n\n来自日课：不要遵守规矩\n\n读者 闲来垂钓：万老师，那么延伸到当行动主体是国家时，这个守规\n\n矩和不守规矩的平衡如何把握呢？\n\n万维钢回复——\n\n追责手段，尤其是如果你是大国，说白了就是没人管得了你。如果说有\n\n人管的时候我就守规矩，没人管我就不守规矩，这不是权力思维——尤\n\n其不是大国该有的权力思维。\n\n没人管的局面下，规矩就是国与国之间签订的协定——说不好听就是\n\n“条约”。对国家来说，是否遵守条约，不是你能力强不强的问题，而\n\n是你有没有信用的问题。\n\n中国从宋朝跟辽国签订《澶渊之盟》开始，承认「蛮夷」也是对等的国\n\n家，有了国际意识。然而也是从宋朝开始，中国就不太愿意遵守国际条\n\n约。对辽也好，对金也好，包括一直到后来大清对列强也好，都是从签\n\f约那一刻就没打算遵守。大清皇帝脑子里根本就没有遵守协议那根弦，\n\n连大臣写给皇帝的奏折都直接说我们签协议都是暂时骗一下对方。\n\n可能有人觉得这很强势，我们中国人就是不要守蛮夷的规矩！可是在国\n\n际社会的角度，这就等于你没有信誉，跟你打交道没意思，咱们永远都\n\n别指望长期合作。\n\n更何况宋和大清对条约的态度一直都是打不过我就签约，签了我就不遵\n\n守，不遵守就再被打，打完我再签……这种形象也太不堪了。\n\n在我看来，没人管的时候能主动维护规矩，甚至为了信誉宁可放弃一点\n\n短期利益，那才是真的强势。\n\n太阳本无事，庸人自扰之\n\n读者 Perseus：如果刘慈欣构建的都是事实上不存在，逻辑上不合理的\n\n情景，那是不是“电车难题”也是个不值得探究的问题？\n\n读者 Bonnie：如果说集体主义理性美学有大问题，请问万 sir，如果真\n\n的有突然的人类大危机，那是不是也要放弃集体主义？\n\n万维钢回复——\n\f这两个问题说的是同一件事——思想实验——的两面，合起来考虑就\n\n对了。\n\n如果你非要实施集体主义美学，你必须设想一种非常非常极端的情境，\n\n因为在已知的人类历史上，集体主义美学从来都没有胜利过。\n\n中国的抗日战争算不算大危机？卢沟桥事变之后，蒋介石发表声明，号\n\n召「如果战端一开，那就是地无分南北，人无分老幼，无论何人，皆有\n\n守土抗战之责任，皆抱定牺牲一切之决心……」那全国人民是不是像他\n\n说的那样牺牲了一切呢？没有啊。农民还在种地，工人还在生产，学生\n\n还在学习，科学家还在搞科研，张爱玲还在写小说，老百姓还在过日子。\n\n集体主义美学的爱好者可能会说，哈！中国人就是不爱国！如果每个中\n\n国人都走上街头对日本人发起自杀式攻击，日本人早就被赶跑了！那你\n\n就太愚蠢了。这不是中国人民不爱国，而是中国人民懂得，世界上有些\n\n更基本的东西比干掉日本人更重要。\n\n跟蒋介石的集体主义理想对比，毛泽东的《论持久战》，恰恰是反对速\n\n胜论、反对消耗战和阵地战、强调经济、政治和文化这些因素，认为「保\n\n存自己」比「消灭敌人」更重要。毛泽东尤其强调了国际形势的重要性，\n\n强调日本那种强制全民为战争服务的模式必定导致其经济崩溃。\n\f这就是在危机之中善于发现和利用有利的外部条件，知道外边除了敌人\n\n还有很多朋友，而没有鼓吹什么外边都是危机、我们必须牺牲一半中国\n\n人和全体五十岁以上的士兵才有出路。\n\n毛泽东说的是与侵略局面持久共存，而不是把日军清零。\n\n如果抗战尚且如此，那到底什么样的危机才能把所有人都动员起来呢？\n\n那也就只有《流浪地球》那种天崩地裂的局面了。\n\n而那样的局面，只存在于幻想之中。这就是思想实验的问题所在：它们\n\n设想的那些极端局面都是事实上不存在、逻辑上不成立的情境。\n\n「电车难题」也是如此。如果全世界只剩下六个人，你救五个还是救一\n\n个？那大概只好“理性”选择，牺牲一个救五个。\n\n可是全世界并没有只剩下六个人！在世界还好好地存在的情况下，如果\n\n我们为了救人就可以随便牺牲一个人，那就必然是人人自危，自己没做\n\n错任何事都会被牺牲掉，这不就是人矿吗？\n\n真实世界中我们不能抽象地考虑五个人和一个人，我们得考虑这些人背\n\n后的人，这些人给社会树立的榜样和预期。那五个人为啥陷入了危险？\n\n如果是他们自己的错，凭什么牺牲别人？就算不是他们自己的错，难道\n\n就能平白牺牲无辜的人吗？\n\n[1]精英日课第四季，《重新思考》2：既承认错误，又维持自行",
  "source_type": "fragment_expression",
  "confidence": "A",
  "tags": [
    "file_upload"
  ],
  "created_at": "2026-06-13T23:07:44.637062",
  "cleaned_content": "",
  "url": null,
  "word_count": 3709,
  "extracted_triples": [],
  "id": "d911bb47-eb2e-49ea-8fd5-c9e88b2d13d2"
}